odoo/addons/partner_contact_old_acc_number/README.rst
odoo/addons/partner_contact_old_acc_number/__init__.py
odoo/addons/partner_contact_old_acc_number/__manifest__.py
odoo/addons/partner_contact_old_acc_number/i18n/es.po
odoo/addons/partner_contact_old_acc_number/models/__init__.py
odoo/addons/partner_contact_old_acc_number/models/res_partner.py
odoo/addons/partner_contact_old_acc_number/static/description/icon.png
odoo/addons/partner_contact_old_acc_number/views/res_partner_views.xml
odoo12_addon_partner_contact_old_acc_number-12.0.1.0.1.dist-info/METADATA
odoo12_addon_partner_contact_old_acc_number-12.0.1.0.1.dist-info/WHEEL
odoo12_addon_partner_contact_old_acc_number-12.0.1.0.1.dist-info/top_level.txt
odoo12_addon_partner_contact_old_acc_number-12.0.1.0.1.dist-info/RECORD
